kso_utils/.ipynb_checkpoints/project-checkpoint.py
kso_utils/.ipynb_checkpoints/widgets-checkpoint.py
kso_utils/.ipynb_checkpoints/zooniverse_utils-checkpoint.py
kso_utils/__init__.py
kso_utils/db_starter/__init__.py
kso_utils/db_starter/cdn_projects_list.csv
kso_utils/db_starter/projects_list.csv
kso_utils/db_starter/schema.py
kso_utils/db_utils.py
kso_utils/frame_utils.py
kso_utils/general.py
kso_utils/koster_utils.py
kso_utils/movie_utils.py
kso_utils/project.py
kso_utils/project_utils.py
kso_utils/server_utils.py
kso_utils/sgu_utils.py
kso_utils/spyfish_utils.py
kso_utils/video_reader.py
kso_utils/widgets.py
kso_utils/yolo_utils.py
kso_utils/zenodo_utils.py
kso_utils/zooniverse_utils.py
kso_utils-0.3.0.dist-info/LICENSE
kso_utils-0.3.0.dist-info/METADATA
kso_utils-0.3.0.dist-info/WHEEL
kso_utils-0.3.0.dist-info/RECORD
