Metadata-Version: 2.1
Name: kso_utils
Version: 0.3.0
Summary: A package containing utility scripts for use with KSO analysis notebooks.
License: MIT
Author: Jurie Germishuys
Author-email: jurie.germishuys@combine.se
Requires-Python: >=3.9,<4.0
Classifier: License :: OSI Approved :: MIT License
Classifier: Programming Language :: Python :: 3
Classifier: Programming Language :: Python :: 3.9
Classifier: Programming Language :: Python :: 3.10
Classifier: Programming Language :: Python :: 3.11
Classifier: Programming Language :: Python :: 3.12
Requires-Dist: av (>=10.0.0,<11.0.0)
Requires-Dist: boto3 (>=1.28.80,<2.0.0)
Requires-Dist: boxmot (==10.0.44)
Requires-Dist: csv-diff (>=1.1,<2.0)
Requires-Dist: dataclass-csv (==1.4.0)
Requires-Dist: ffmpeg-python (==0.2.0)
Requires-Dist: fiftyone (==0.24.0)
Requires-Dist: folium (>=0.12.1,<0.13.0)
Requires-Dist: ftfy (==6.2.0)
Requires-Dist: gdown (>=5.1.0,<6.0.0)
Requires-Dist: imagesize (==1.4.1)
Requires-Dist: ipyfilechooser (>=0.4.4,<0.5.0)
Requires-Dist: ipysheet (>=0.4.4,<0.5.0)
Requires-Dist: ipython (>=7.34.0,<8.0.0)
Requires-Dist: ipywidgets (==7.6.5)
Requires-Dist: jupyter-bbox-widget (==0.5.0)
Requires-Dist: mlflow (==2.13.1)
Requires-Dist: more-itertools (>=10.1.0,<11.0.0)
Requires-Dist: natsort (>=8.1.0,<9.0.0)
Requires-Dist: notebook (>=6.5.5,<7.0.0)
Requires-Dist: numpy (>=1.22.0,<1.24.5)
Requires-Dist: pandas (>=1.5.3,<2.0.0)
Requires-Dist: pims (==0.6.1)
Requires-Dist: requests (>=2.28.2,<3.0.0)
Requires-Dist: tqdm (>=4.64.1,<5.0.0)
Requires-Dist: ultralytics (>=8.0.200,<9.0.0)
Requires-Dist: wandb (==0.17.0)
Requires-Dist: yolov5 (==7.0.13)
